promptify/__init__.py
promptify_llm-0.1.0.dist-info/METADATA
promptify_llm-0.1.0.dist-info/WHEEL
promptify_llm-0.1.0.dist-info/top_level.txt
promptify_llm-0.1.0.dist-info/RECORD
